{
  "packageId": "com.welokl.app",
  "host": "welokl.com",
  "name": "Welokl",
  "launcherName": "Welokl",
  "display": "standalone",
  "themeColor": "#FF3008",
  "navigationColor": "#FF3008",
  "navigationColorDark": "#FF3008",
  "navigationDividerColor": "#FF3008",
  "navigationDividerColorDark": "#FF3008",
  "backgroundColor": "#FFFBF5",
  "startUrl": "/?source=twa",
  "iconUrl": "https://welokl.com/icons/icon-512.png",
  "maskableIconUrl": "https://welokl.com/icons/icon-512-maskable.png",
  "splashScreenFadeOutDuration": 300,
  "signingKey": {
    "path": "./welokl-release-key.keystore",
    "alias": "welokl"
  },
  "appVersionCode": 1,
  "appVersionName": "1.0.0",
  "shortcuts": [
    {
      "name": "Browse Shops",
      "short_name": "Shops",
      "url": "/stores?source=shortcut",
      "icons": [{ "src": "https://welokl.com/icons/icon-96.png", "sizes": "96x96" }]
    },
    {
      "name": "My Orders",
      "short_name": "Orders",
      "url": "/orders/history?source=shortcut",
      "icons": [{ "src": "https://welokl.com/icons/icon-96.png", "sizes": "96x96" }]
    }
  ],
  "enableNotifications": true,
  "features": {
    "locationDelegation": { "enabled": false },
    "playBilling": { "enabled": false }
  },
  "alphaDependencies": { "enabled": false },
  "enableSiteSettingsShortcut": true,
  "isChromeOSOnly": false,
  "isMetaQuestOnly": false,
  "fullScopeUrl": "https://welokl.com/",
  "minSdkVersion": 19,
  "orientation": "portrait",
  "fingerprints": []
}
